{
  "robot_params": {
    "R": 0.088,
    "l": 0.03,
    "mw": 0.322,
    "mp": 2.751,
    "M": 8.4,
    "IM": 0.112177,
    "g": 9.81
  },
  "leg_params": {
    "l1": 0.21,
    "l2": 0.24,
    "l3": 0.24,
    "l4": 0.21,
    "l5": 0.0
  },
  "Q": [
    50.0,
    1.0,
    700.0,
    100.0,
    7000.0,
    1.0
  ],
  "R": [
    12.0,
    1.0
  ],
  "dt": 0.02,
  "N": 15,
  "u_min": [
    -4.0,
    -10.0
  ],
  "u_max": [
    4.0,
    10.0
  ],
  "L0_range": {
    "min": 0.1,
    "max": 0.4,
    "n_points": 30
  },
  "L0_values": [
    0.1,
    0.11034482758620691,
    0.1206896551724138,
    0.1310344827586207,
    0.1413793103448276,
    0.1517241379310345,
    0.1620689655172414,
    0.1724137931034483,
    0.1827586206896552,
    0.1931034482758621,
    0.20344827586206898,
    0.2137931034482759,
    0.2241379310344828,
    0.23448275862068968,
    0.24482758620689657,
    0.2551724137931035,
    0.2655172413793104,
    0.27586206896551724,
    0.28620689655172415,
    0.29655172413793107,
    0.306896551724138,
    0.3172413793103449,
    0.32758620689655177,
    0.33793103448275863,
    0.34827586206896555,
    0.35862068965517246,
    0.3689655172413794,
    0.3793103448275863,
    0.3896551724137931,
    0.4
  ],
  "Ad_table": [
    [
      [
        1.0,
        0.02,
        0.0,
        0.0,
        0.0,
        0.0
      ],
      [
        1.0984081616315218,
        1.0,
        0.0,
        0.0,
        -0.009764311835371407,
        0.0
      ],
      [
        0.0,
        0.0,
        1.0,
        0.02,
        0.0,
        0.0
      ],
      [
        -0.09184349312734455,
        0.0,
        0.0,
        1.0,
        0.009258962160876126,
        0.0
      ],
      [
        0.0,
        0.0,
        0.0,
        0.0,
        1.0,
        0.02
      ],
      [
        -0.037877392994727595,
        0.0,
        0.0,
        0.0,
        0.39549347481316044,
        1.0
      ]
    ],
    [
      [
        1.0,
        0.02,
        0.0,
        0.0,
        0.0,
        0.0
      ],
      [
        0.9960166385772228,
        1.0,
        0.0,
        0.0,
        -0.008854101227580798,
        0.0
      ],
      [
        0.0,
        0.0,
        1.0,
        0.02,
        0.0,
        0.0
      ],
      [
        -0.09189739817942286,
        0.0,
        0.0,
        1.0,
        0.009259441350449165,
        0.0
      ],
      [
        0.0,
        0.0,
        0.0,
        0.0,
        1.0,
        0.02
      ],
      [
        -0.03789962410520085,
        0.0,
        0.0,
        0.0,
        0.3954936724368696,
        1.0
      ]
    ],
    [
      [
        1.0,
        0.02,
        0.0,
        0.0,
        0.0,
        0.0
      ],
      [
        0.9110469896033828,
        1.0,
        0.0,
        0.0,
        -0.00809876256741436,
        0.0
      ],
      [
        0.0,
        0.0,
        1.0,
        0.02,
        0.0,
        0.0
      ],
      [
        -0.0919380875917447,
        0.0,
        0.0,
        1.0,
        0.009259803059442403,
        0.0
      ],
      [
        0.0,
        0.0,
        0.0,
        0.0,
        1.0,
        0.02
      ],
      [
        -0.03791640492231455,
        0.0,
        0.0,
        0.0,
        0.39549382161013397,
        1.0
      ]
    ],
    [
      [
        1.0,
        0.02,
        0.0,
        0.0,
        0.0,
        0.0
      ],
      [
        0.8394093931528026,
        1.0,
        0.0,
        0.0,
        -0.007461939339661795,
        0.0
      ],
      [
        0.0,
        0.0,
        1.0,
        0.02,
        0.0,
        0.0
      ],
      [
        -0.09196955080600736,
        0.0,
        0.0,
        1.0,
        0.009260082752043148,
        0.0
      ],
      [
        0.0,
        0.0,
        0.0,
        0.0,
        1.0,
        0.02
      ],
      [
        -0.03792938074118767,
        0.0,
        0.0,
        0.0,
        0.3954939369588234,
        1.0
      ]
    ],
    [
      [
        1.0,
        0.02,
        0.0,
        0.0,
        0.0,
        0.0
      ],
      [
        0.778199218666176,
        1.0,
        0.0,
        0.0,
        -0.006917810797957256,
        0.0
      ],
      [
        0.0,
        0.0,
        1.0,
        0.02,
        0.0,
        0.0
      ],
      [
        -0.09199437879359675,
        0.0,
        0.0,
        1.0,
        0.009260303460720973,
        0.0
      ],
      [
        0.0,
        0.0,
        0.0,
        0.0,
        1.0,
        0.02
      ],
      [
        -0.03793962011047959,
        0.0,
        0.0,
        0.0,
        0.39549402798181305,
        1.0
      ]
    ],
    [
      [
        1.0,
        0.02,
        0.0,
        0.0,
        0.0,
        0.0
      ],
      [
        0.725297313956005,
        1.0,
        0.0,
        0.0,
        -0.006447538714847517,
        0.0
      ],
      [
        0.0,
        0.0,
        1.0,
        0.02,
        0.0,
        0.0
      ],
      [
        -0.09201431334736747,
        0.0,
        0.0,
        1.0,
        0.009260480669163256,
        0.0
      ],
      [
        0.0,
        0.0,
        0.0,
        0.0,
        1.0,
        0.02
      ],
      [
        -0.03794784136711559,
        0.0,
        0.0,
        0.0,
        0.3954941010647673,
        1.0
      ]
    ],
    [
      [
        1.0,
        0.02,
        0.0,
        0.0,
        0.0,
        0.0
      ],
      [
        0.6791216319106037,
        1.0,
        0.0,
        0.0,
        -0.006037059464554458,
        0.0
      ],
      [
        0.0,
        0.0,
        1.0,
        0.02,
        0.0,
        0.0
      ],
      [
        -0.09203056029414118,
        0.0,
        0.0,
        1.0,
        0.009260625096581234,
        0.0
      ],
      [
        0.0,
        0.0,
        0.0,
        0.0,
        1.0,
        0.02
      ],
      [
        -0.03795454180899729,
        0.0,
        0.0,
        0.0,
        0.39549416062842147,
        1.0
      ]
    ],
    [
      [
        1.0,
        0.02,
        0.0,
        0.0,
        0.0,
        0.0
      ],
      [
        0.6384673913662681,
        1.0,
        0.0,
        0.0,
        -0.005675663131231999,
        0.0
      ],
      [
        0.0,
        0.0,
        1.0,
        0.02,
        0.0,
        0.0
      ],
      [
        -0.09204397581145161,
        0.0,
        0.0,
        1.0,
        0.009260744353974823,
        0.0
      ],
      [
        0.0,
        0.0,
        0.0,
        0.0,
        1.0,
        0.02
      ],
      [
        -0.03796007453433355,
        0.0,
        0.0,
        0.0,
        0.3954942098116463,
        1.0
      ]
    ],
    [
      [
        1.0,
        0.02,
        0.0,
        0.0,
        0.0,
        0.0
      ],
      [
        0.602401055823821,
        1.0,
        0.0,
        0.0,
        -0.005355051031561787,
        0.0
      ],
      [
        0.0,
        0.0,
        1.0,
        0.02,
        0.0,
        0.0
      ],
      [
        -0.0920551813584889,
        0.0,
        0.0,
        1.0,
        0.009260843965812554,
        0.0
      ],
      [
        0.0,
        0.0,
        0.0,
        0.0,
        1.0,
        0.02
      ],
      [
        -0.03796469584058403,
        0.0,
        0.0,
        0.0,
        0.39549425089280077,
        1.0
      ]
    ],
    [
      [
        1.0,
        0.02,
        0.0,
        0.0,
        0.0,
        0.0
      ],
      [
        0.5701881317727141,
        1.0,
        0.0,
        0.0,
        -0.005068693877134845,
        0.0
      ],
      [
        0.0,
        0.0,
        1.0,
        0.02,
        0.0,
        0.0
      ],
      [
        -0.09206463684252263,
        0.0,
        0.0,
        1.0,
        0.009260928020445326,
        0.0
      ],
      [
        0.0,
        0.0,
        0.0,
        0.0,
        1.0,
        0.02
      ],
      [
        -0.037968595399197204,
        0.0,
        0.0,
        0.0,
        0.39549428555797134,
        1.0
      ]
    ],
    [
      [
        1.0,
        0.02,
        0.0,
        0.0,
        0.0,
        0.0
      ],
      [
        0.5412428460200496,
        1.0,
        0.0,
        0.0,
        -0.004811384430496032,
        0.0
      ],
      [
        0.0,
        0.0,
        1.0,
        0.02,
        0.0,
        0.0
      ],
      [
        -0.09207268850220998,
        0.0,
        0.0,
        1.0,
        0.009260999595765618,
        0.0
      ],
      [
        0.0,
        0.0,
        0.0,
        0.0,
        1.0,
        0.02
      ],
      [
        -0.03797191600327984,
        0.0,
        0.0,
        0.0,
        0.39549431507651917,
        1.0
      ]
    ],
    [
      [
        1.0,
        0.02,
        0.0,
        0.0,
        0.0,
        0.0
      ],
      [
        0.5150923445995101,
        1.0,
        0.0,
        0.0,
        -0.00457891925093819,
        0.0
      ],
      [
        0.0,
        0.0,
        1.0,
        0.02,
        0.0,
        0.0
      ],
      [
        -0.09207960101901412,
        0.0,
        0.0,
        1.0,
        0.009261061044662304,
        0.0
      ],
      [
        0.0,
        0.0,
        0.0,
        0.0,
        1.0,
        0.02
      ],
      [
        -0.03797476681074213,
        0.0,
        0.0,
        0.0,
        0.3954943404188045,
        1.0
      ]
    ],
    [
      [
        1.0,
        0.02,
        0.0,
        0.0,
        0.0,
        0.0
      ],
      [
        0.4913507519171301,
        1.0,
        0.0,
        0.0,
        -0.004367868092983583,
        0.0
      ],
      [
        0.0,
        0.0,
        1.0,
        0.02,
        0.0,
        0.0
      ],
      [
        -0.09208557952490727,
        0.0,
        0.0,
        1.0,
        0.00926111419065838,
        0.0
      ],
      [
        0.0,
        0.0,
        0.0,
        0.0,
        1.0,
        0.02
      ],
      [
        -0.037977232420547756,
        0.0,
        0.0,
        0.0,
        0.39549436233687074,
        1.0
      ]
    ],
    [
      [
        1.0,
        0.02,
        0.0,
        0.0,
        0.0,
        0.0
      ],
      [
        0.46970006278855764,
        1.0,
        0.0,
        0.0,
        -0.004175404045932012,
        0.0
      ],
      [
        0.0,
        0.0,
        1.0,
        0.02,
        0.0,
        0.0
      ],
      [
        -0.09209078498212353,
        0.0,
        0.0,
        1.0,
        0.009261160464629463,
        0.0
      ],
      [
        0.0,
        0.0,
        0.0,
        0.0,
        1.0,
        0.02
      ],
      [
        -0.037979379215513726,
        0.0,
        0.0,
        0.0,
        0.39549438142082916,
        1.0
      ]
    ],
    [
      [
        1.0,
        0.02,
        0.0,
        0.0,
        0.0,
        0.0
      ],
      [
        0.4498758570524289,
        1.0,
        0.0,
        0.0,
        -0.003999176543754133,
        0.0
      ],
      [
        0.0,
        0.0,
        1.0,
        0.02,
        0.0,
        0.0
      ],
      [
        -0.09209534512143618,
        0.0,
        0.0,
        1.0,
        0.009261201002039704,
        0.0
      ],
      [
        0.0,
        0.0,
        0.0,
        0.0,
        1.0,
        0.02
      ],
      [
        -0.0379812598733913,
        0.0,
        0.0,
        0.0,
        0.39549439813895865,
        1.0
      ]
    ],
    [
      [
        1.0,
        0.02,
        0.0,
        0.0,
        0.0,
        0.0
      ],
      [
        0.4316564747871804,
        1.0,
        0.0,
        0.0,
        -0.003837215138058206,
        0.0
      ],
      [
        0.0,
        0.0,
        1.0,
        0.02,
        0.0,
        0.0
      ],
      [
        -0.09209936234634597,
        0.0,
        0.0,
        1.0,
        0.009261236713206191,
        0.0
      ],
      [
        0.0,
        0.0,
        0.0,
        0.0,
        1.0,
        0.02
      ],
      [
        -0.03798291662665136,
        0.0,
        0.0,
        0.0,
        0.3954944128666855,
        1.0
      ]
    ],
    [
      [
        1.0,
        0.02,
        0.0,
        0.0,
        0.0,
        0.0
      ],
      [
        0.41485471249643896,
        1.0,
        0.0,
        0.0,
        -0.003687855681235807,
        0.0
      ],
      [
        0.0,
        0.0,
        1.0,
        0.02,
        0.0,
        0.0
      ],
      [
        -0.09210291952810255,
        0.0,
        0.0,
        1.0,
        0.009261268334813841,
        0.0
      ],
      [
        0.0,
        0.0,
        0.0,
        0.0,
        1.0,
        0.02
      ],
      [
        -0.03798438365242281,
        0.0,
        0.0,
        0.0,
        0.39549442590782785,
        1.0
      ]
    ],
    [
      [
        1.0,
        0.02,
        0.0,
        0.0,
        0.0,
        0.0
      ],
      [
        0.39931138119423126,
        1.0,
        0.0,
        0.0,
        -0.003549683060987035,
        0.0
      ],
      [
        0.0,
        0.0,
        1.0,
        0.02,
        0.0,
        0.0
      ],
      [
        -0.09210608431100142,
        0.0,
        0.0,
        1.0,
        0.009261296468187389,
        0.0
      ],
      [
        0.0,
        0.0,
        0.0,
        0.0,
        1.0,
        0.02
      ],
      [
        -0.03798568884804984,
        0.0,
        0.0,
        0.0,
        0.3954944375103792,
        1.0
      ]
    ],
    [
      [
        1.0,
        0.02,
        0.0,
        0.0,
        0.0,
        0.0
      ],
      [
        0.3848902570706065,
        1.0,
        0.0,
        0.0,
        -0.0034214863142053064,
        0.0
      ],
      [
        0.0,
        0.0,
        1.0,
        0.02,
        0.0,
        0.0
      ],
      [
        -0.09210891235002493,
        0.0,
        0.0,
        1.0,
        0.009261321608072425,
        0.0
      ],
      [
        0.0,
        0.0,
        0.0,
        0.0,
        1.0,
        0.02
      ],
      [
        -0.03798685516633601,
        0.0,
        0.0,
        0.0,
        0.3954944478783788,
        1.0
      ]
    ],
    [
      [
        1.0,
        0.02,
        0.0,
        0.0,
        0.0,
        0.0
      ],
      [
        0.371474085867255,
        1.0,
        0.0,
        0.0,
        -0.003302223107828844,
        0.0
      ],
      [
        0.0,
        0.0,
        1.0,
        0.02,
        0.0,
        0.0
      ],
      [
        -0.092111449773,
        0.0,
        0.0,
        1.0,
        0.0092613441645228,
        0.0
      ],
      [
        0.0,
        0.0,
        0.0,
        0.0,
        1.0,
        0.02
      ],
      [
        -0.03798790163096781,
        0.0,
        0.0,
        0.0,
        0.3954944571809382,
        1.0
      ]
    ],
    [
      [
        1.0,
        0.02,
        0.0,
        0.0,
        0.0,
        0.0
      ],
      [
        0.3589613931346326,
        1.0,
        0.0,
        0.0,
        -0.0031909913835852463,
        0.0
      ],
      [
        0.0,
        0.0,
        1.0,
        0.02,
        0.0,
        0.0
      ],
      [
        -0.09211373507248619,
        0.0,
        0.0,
        1.0,
        0.009261364479718549,
        0.0
      ],
      [
        0.0,
        0.0,
        0.0,
        0.0,
        1.0,
        0.02
      ],
      [
        -0.037988844116753115,
        0.0,
        0.0,
        0.0,
        0.3954944655591761,
        1.0
      ]
    ],
    [
      [
        1.0,
        0.02,
        0.0,
        0.0,
        0.0,
        0.0
      ],
      [
        0.34726391697010833,
        1.0,
        0.0,
        0.0,
        -0.0030870065362880567,
        0.0
      ],
      [
        0.0,
        0.0,
        1.0,
        0.02,
        0.0,
        0.0
      ],
      [
        -0.0921158005734834,
        0.0,
        0.0,
        1.0,
        0.009261382841013138,
        0.0
      ],
      [
        0.0,
        0.0,
        0.0,
        0.0,
        1.0,
        0.02
      ],
      [
        -0.03798969595492183,
        0.0,
        0.0,
        0.0,
        0.3954944731316013,
        1.0
      ]
    ],
    [
      [
        1.0,
        0.02,
        0.0,
        0.0,
        0.0,
        0.0
      ],
      [
        0.3363045260205009,
        1.0,
        0.0,
        0.0,
        -0.0029895829058966383,
        0.0
      ],
      [
        0.0,
        0.0,
        1.0,
        0.02,
        0.0,
        0.0
      ],
      [
        -0.09211767358225871,
        0.0,
        0.0,
        1.0,
        0.009261399491145931,
        0.0
      ],
      [
        0.0,
        0.0,
        0.0,
        0.0,
        1.0,
        0.02
      ],
      [
        -0.037990468406916625,
        0.0,
        0.0,
        0.0,
        0.3954944799983221,
        1.0
      ]
    ],
    [
      [
        1.0,
        0.02,
        0.0,
        0.0,
        0.0,
        0.0
      ],
      [
        0.3260155190355124,
        1.0,
        0.0,
        0.0,
        -0.002898118661377077,
        0.0
      ],
      [
        0.0,
        0.0,
        1.0,
        0.02,
        0.0,
        0.0
      ],
      [
        -0.09211937729307489,
        0.0,
        0.0,
        1.0,
        0.009261414636302593,
        0.0
      ],
      [
        0.0,
        0.0,
        0.0,
        0.0,
        1.0,
        0.02
      ],
      [
        -0.03799117103833827,
        0.0,
        0.0,
        0.0,
        0.39549448624437206,
        1.0
      ]
    ],
    [
      [
        1.0,
        0.02,
        0.0,
        0.0,
        0.0,
        0.0
      ],
      [
        0.3163372268340341,
        1.0,
        0.0,
        0.0,
        -0.0028120833728658306,
        0.0
      ],
      [
        0.0,
        0.0,
        1.0,
        0.02,
        0.0,
        0.0
      ],
      [
        -0.09212093150941444,
        0.0,
        0.0,
        1.0,
        0.009261428452526407,
        0.0
      ],
      [
        0.0,
        0.0,
        0.0,
        0.0,
        1.0,
        0.02
      ],
      [
        -0.03799181201638775,
        0.0,
        0.0,
        0.0,
        0.39549449194235375,
        1.0
      ]
    ],
    [
      [
        1.0,
        0.02,
        0.0,
        0.0,
        0.0,
        0.0
      ],
      [
        0.30721685575970786,
        1.0,
        0.0,
        0.0,
        -0.002731007730554737,
        0.0
      ],
      [
        0.0,
        0.0,
        1.0,
        0.02,
        0.0,
        0.0
      ],
      [
        -0.09212235322183496,
        0.0,
        0.0,
        1.0,
        0.009261441090855124,
        0.0
      ],
      [
        0.0,
        0.0,
        0.0,
        0.0,
        1.0,
        0.02
      ],
      [
        -0.03799239834818155,
        0.0,
        0.0,
        0.0,
        0.3954944971545568,
        1.0
      ]
    ],
    [
      [
        1.0,
        0.02,
        0.0,
        0.0,
        0.0,
        0.0
      ],
      [
        0.29860752533329343,
        1.0,
        0.0,
        0.0,
        -0.0026544749898908294,
        0.0
      ],
      [
        0.0,
        0.0,
        1.0,
        0.02,
        0.0,
        0.0
      ],
      [
        -0.09212365707412225,
        0.0,
        0.0,
        1.0,
        0.009261452681464853,
        0.0
      ],
      [
        0.0,
        0.0,
        0.0,
        0.0,
        1.0,
        0.02
      ],
      [
        -0.03799293607299815,
        0.0,
        0.0,
        0.0,
        0.3954945019346678,
        1.0
      ]
    ],
    [
      [
        1.0,
        0.02,
        0.0,
        0.0,
        0.0,
        0.0
      ],
      [
        0.29046746310361693,
        1.0,
        0.0,
        0.0,
        -0.002582113814194692,
        0.0
      ],
      [
        0.0,
        0.0,
        1.0,
        0.02,
        0.0,
        0.0
      ],
      [
        -0.09212485574175272,
        0.0,
        0.0,
        1.0,
        0.00926146333703437,
        0.0
      ],
      [
        0.0,
        0.0,
        0.0,
        0.0,
        1.0,
        0.02
      ],
      [
        -0.037993430418360695,
        0.0,
        0.0,
        0.0,
        0.3954945063291564,
        1.0
      ]
    ],
    [
      [
        1.0,
        0.02,
        0.0,
        0.0,
        0.0,
        0.0
      ],
      [
        0.2827593275395453,
        1.0,
        0.0,
        0.0,
        -0.002513592255500959,
        0.0
      ],
      [
        0.0,
        0.0,
        1.0,
        0.02,
        0.0,
        0.0
      ],
      [
        -0.09212596024102165,
        0.0,
        0.0,
        1.0,
        0.009261473155493175,
        0.0
      ],
      [
        0.0,
        0.0,
        0.0,
        0.0,
        1.0,
        0.02
      ],
      [
        -0.03799388592752581,
        0.0,
        0.0,
        0.0,
        0.3954945103784103,
        1.0
      ]
    ],
    [
      [
        1.0,
        0.02,
        0.0,
        0.0,
        0.0,
        0.0
      ],
      [
        0.27544963582543736,
        1.0,
        0.0,
        0.0,
        -0.002448612667939477,
        0.0
      ],
      [
        0.0,
        0.0,
        1.0,
        0.02,
        0.0,
        0.0
      ],
      [
        -0.09212698018298157,
        0.0,
        0.0,
        1.0,
        0.009261482222278818,
        0.0
      ],
      [
        0.0,
        0.0,
        0.0,
        0.0,
        1.0,
        0.02
      ],
      [
        -0.03799430656421036,
        0.0,
        0.0,
        0.0,
        0.3954945141176649,
        1.0
      ]
    ]
  ],
  "Bd_table": [
    [
      [
        0.0,
        0.0
      ],
      [
        -0.005707345332448958,
        0.11058985421869398
      ],
      [
        0.0,
        0.0
      ],
      [
        0.0189166558908849,
        -0.005831887729156894
      ],
      [
        0.0,
        0.0
      ],
      [
        -0.038611057418553016,
        0.15603173105586787
      ]
    ],
    [
      [
        0.0,
        0.0
      ],
      [
        0.0045617882153172595,
        0.09054377235449547
      ],
      [
        0.0,
        0.0
      ],
      [
        0.018018542681767558,
        -0.004938921693286353
      ],
      [
        0.0,
        0.0
      ],
      [
        -0.03898145041883148,
        0.1564000012982106
      ]
    ],
    [
      [
        0.0,
        0.0
      ],
      [
        0.011552244844411641,
        0.07543991100495302
      ],
      [
        0.0,
        0.0
      ],
      [
        0.017273643711991013,
        -0.004197907989295781
      ],
      [
        0.0,
        0.0
      ],
      [
        -0.03928865597100351,
        0.15670560451869806
      ]
    ],
    [
      [
        0.0,
        0.0
      ],
      [
        0.016369630901350202,
        0.06378214346800343
      ],
      [
        0.0,
        0.0
      ],
      [
        0.01664590372706303,
        -0.003573172298185676
      ],
      [
        0.0,
        0.0
      ],
      [
        -0.03954754370815279,
        0.15696325324790308
      ]
    ],
    [
      [
        0.0,
        0.0
      ],
      [
        0.019707371780519106,
        0.05459969304116841
      ],
      [
        0.0,
        0.0
      ],
      [
        0.01610973995317971,
        -0.0030393792474269
      ],
      [
        0.0,
        0.0
      ],
      [
        -0.03976866428274545,
        0.1571833961069449
      ]
    ],
    [
      [
        0.0,
        0.0
      ],
      [
        0.022015128837173378,
        0.047240549182523905
      ],
      [
        0.0,
        0.0
      ],
      [
        0.015646502497946677,
        -0.0025780452613103928
      ],
      [
        0.0,
        0.0
      ],
      [
        -0.03995970914117008,
        0.15737365595115324
      ]
    ],
    [
      [
        0.0,
        0.0
      ],
      [
        0.0235928061742581,
        0.04125374457233
      ],
      [
        0.0,
        0.0
      ],
      [
        0.015242277700197709,
        -0.0021753718181478994
      ],
      [
        0.0,
        0.0
      ],
      [
        -0.040126416449452904,
        0.15753972346160885
      ]
    ],
    [
      [
        0.0,
        0.0
      ],
      [
        0.024645273124448207,
        0.03631937024554015
      ],
      [
        0.0,
        0.0
      ],
      [
        0.014886476000021133,
        -0.001820851110923374
      ],
      [
        0.0,
        0.0
      ],
      [
        -0.040273153473131845,
        0.1576859321879439
      ]
    ],
    [
      [
        0.0,
        0.0
      ],
      [
        0.02531538473139698,
        0.03220543157124114
      ],
      [
        0.0,
        0.0
      ],
      [
        0.014570896130386188,
        -0.0015063412132057658
      ],
      [
        0.0,
        0.0
      ],
      [
        -0.04040330251620897,
        0.15781563996136305
      ]
    ],
    [
      [
        0.0,
        0.0
      ],
      [
        0.02570453658276491,
        0.028740399176502375
      ],
      [
        0.0,
        0.0
      ],
      [
        0.014289088326806547,
        -0.0012254362751754027
      ],
      [
        0.0,
        0.0
      ],
      [
        -0.04051952354136496,
        0.1579314886335949
      ]
    ],
    [
      [
        0.0,
        0.0
      ],
      [
        0.025885812538257686,
        0.02579525611202941
      ],
      [
        0.0,
        0.0
      ],
      [
        0.014035910809527041,
        -0.0009730275779922957
      ],
      [
        0.0,
        0.0
      ],
      [
        -0.040623937082192835,
        0.15803558510350196
      ]
    ],
    [
      [
        0.0,
        0.0
      ],
      [
        0.02591259834179957,
        0.02327146574003498
      ],
      [
        0.0,
        0.0
      ],
      [
        0.01380721444498198,
        -0.0007449912614425637
      ],
      [
        0.0,
        0.0
      ],
      [
        -0.0407182542927145,
        0.15812963010206318
      ]
    ],
    [
      [
        0.0,
        0.0
      ],
      [
        0.025824345846831357,
        0.021092730522726262
      ],
      [
        0.0,
        0.0
      ],
      [
        0.01359961438172785,
        -0.0005379620612968558
      ],
      [
        0.0,
        0.0
      ],
      [
        -0.04080387112754792,
        0.15821501150588713
      ]
    ],
    [
      [
        0.0,
        0.0
      ],
      [
        0.02565050419932466,
        0.019199236297975823
      ],
      [
        0.0,
        0.0
      ],
      [
        0.013410321920435007,
        -0.0003491666478518083
      ],
      [
        0.0,
        0.0
      ],
      [
        -0.040881937680802685,
        0.15829287307045922
      ]
    ],
    [
      [
        0.0,
        0.0
      ],
      [
        0.02541324682827895,
        0.017543561235604528
      ],
      [
        0.0,
        0.0
      ],
      [
        0.01323701887295591,
        -0.0001762990294497057
      ],
      [
        0.0,
        0.0
      ],
      [
        -0.040953410001955,
        0.15836416581527243
      ]
    ],
    [
      [
        0.0,
        0.0
      ],
      [
        0.025129392285459313,
        0.01608772138331109
      ],
      [
        0.0,
        0.0
      ],
      [
        0.01307776239571094,
        -1.7426140602939223e-05
      ],
      [
        0.0,
        0.0
      ],
      [
        -0.04101908934373699,
        0.15842968696045265
      ]
    ],
    [
      [
        0.0,
        0.0
      ],
      [
        0.024811776109177956,
        0.014801005905550686
      ],
      [
        0.0,
        0.0
      ],
      [
        0.012930912012884278,
        0.0001290845814671556
      ],
      [
        0.0,
        0.0
      ],
      [
        -0.041079652258673605,
        0.1584901097950904
      ]
    ],
    [
      [
        0.0,
        0.0
      ],
      [
        0.024470242997662203,
        0.013658369798035712
      ],
      [
        0.0,
        0.0
      ],
      [
        0.012795073021501926,
        0.00026462138065710863
      ],
      [
        0.0,
        0.0
      ],
      [
        -0.041135673939528695,
        0.15854600684814618
      ]
    ],
    [
      [
        0.0,
        0.0
      ],
      [
        0.024112372632389426,
        0.012639225924085163
      ],
      [
        0.0,
        0.0
      ],
      [
        0.012669052144482476,
        0.0003903722197813786
      ],
      [
        0.0,
        0.0
      ],
      [
        -0.04118764650853571,
        0.1585978680501839
      ]
    ],
    [
      [
        0.0,
        0.0
      ],
      [
        0.023744016222952948,
        0.011726526943906895
      ],
      [
        0.0,
        0.0
      ],
      [
        0.012551822448032782,
        0.0005073596280753353
      ],
      [
        0.0,
        0.0
      ],
      [
        -0.04123599348589774,
        0.15864611510491256
      ]
    ],
    [
      [
        0.0,
        0.0
      ],
      [
        0.02336969693466603,
        0.010906060311474857
      ],
      [
        0.0,
        0.0
      ],
      [
        0.012442495342189176,
        0.0006164685200053517
      ],
      [
        0.0,
        0.0
      ],
      [
        -0.041281081337110816,
        0.15869111296200755
      ]
    ],
    [
      [
        0.0,
        0.0
      ],
      [
        0.02299291135212464,
        0.010165901673618223
      ],
      [
        0.0,
        0.0
      ],
      [
        0.01234029805092403,
        0.0007184685850168482
      ],
      [
        0.0,
        0.0
      ],
      [
        -0.0413232287645707,
        0.15873317905092008
      ]
    ],
    [
      [
        0.0,
        0.0
      ],
      [
        0.02261635826098559,
        0.009495987286809284
      ],
      [
        0.0,
        0.0
      ],
      [
        0.012244555344964997,
        0.0008140324450182665
      ],
      [
        0.0,
        0.0
      ],
      [
        -0.041362714241184255,
        0.1587725907692478
      ]
    ],
    [
      [
        0.0,
        0.0
      ],
      [
        0.022242113549915052,
        0.008887776746517863
      ],
      [
        0.0,
        0.0
      ],
      [
        0.012154674625420468,
        0.0009037504841757964
      ],
      [
        0.0,
        0.0
      ],
      [
        -0.04139978216206698,
        0.15880959159872596
      ]
    ],
    [
      [
        0.0,
        0.0
      ],
      [
        0.02187176482418415,
        0.008333984881088698
      ],
      [
        0.0,
        0.0
      ],
      [
        0.012070133662583598,
        0.0009881430412426243
      ],
      [
        0.0,
        0.0
      ],
      [
        -0.04143464790121177,
        0.15884439613349485
      ]
    ],
    [
      [
        0.0,
        0.0
      ],
      [
        0.021506515651487406,
        0.0078283670722182
      ],
      [
        0.0,
        0.0
      ],
      [
        0.011990470454534725,
        0.001067670495779475
      ],
      [
        0.0,
        0.0
      ],
      [
        -0.04146750199392692,
        0.1588771942397819
      ]
    ],
    [
      [
        0.0,
        0.0
      ],
      [
        0.021147266746774748,
        0.007365546179477961
      ],
      [
        0.0,
        0.0
      ],
      [
        0.011915274790052293,
        0.0011427416607326045
      ],
      [
        0.0,
        0.0
      ],
      [
        -0.04149851361639595,
        0.15890815451710455
      ]
    ],
    [
      [
        0.0,
        0.0
      ],
      [
        0.020794679523284093,
        0.0069408721088878005
      ],
      [
        0.0,
        0.0
      ],
      [
        0.011844181190858265,
        0.0012137208040505704
      ],
      [
        0.0,
        0.0
      ],
      [
        -0.04152783349638293,
        0.15893742719407197
      ]
    ],
    [
      [
        0.0,
        0.0
      ],
      [
        0.020449226072736908,
        0.006550307178440549
      ],
      [
        0.0,
        0.0
      ],
      [
        0.011776862977148656,
        0.001280933553636338
      ],
      [
        0.0,
        0.0
      ],
      [
        -0.04155559636068131,
        0.15896514656366073
      ]
    ],
    [
      [
        0.0,
        0.0
      ],
      [
        0.020111228638859623,
        0.006190332007105315
      ],
      [
        0.0,
        0.0
      ],
      [
        0.011713027253266742,
        0.0013446718874264765
      ],
      [
        0.0,
        0.0
      ],
      [
        -0.04158192300308401,
        0.15899143304118452
      ]
    ]
  ],
  "P_table": [
    [
      [
        748808.3264319905,
        96626.43261213833,
        -58734.051018024955,
        -47437.58839931857,
        -389126.45576079516,
        -66821.12967629661
      ],
      [
        96626.43261213833,
        12487.114742487845,
        -7344.66219648143,
        -5939.882821073004,
        -50230.75116472754,
        -8627.878849580959
      ],
      [
        -58734.051018024955,
        -7344.66219648143,
        28031.171359326,
        8807.026399657352,
        31078.675480526374,
        5268.236360456251
      ],
      [
        -47437.58839931857,
        -5939.882821073004,
        8807.026399657352,
        6278.4903188723065,
        24908.056034430014,
        4231.1190409432675
      ],
      [
        -389126.45576079516,
        -50230.75116472754,
        31078.675480526374,
        24908.056034430014,
        230212.17811977264,
        35544.62124903458
      ],
      [
        -66821.12967629661,
        -8627.878849580959,
        5268.236360456251,
        4231.1190409432675,
        35544.62124903458,
        6012.639298930761
      ]
    ],
    [
      [
        644714.6354473297,
        86274.17007594221,
        -68820.74667791968,
        -55871.19231256805,
        -283213.87856535264,
        -49431.653988162696
      ],
      [
        86274.17007594221,
        11566.173675140431,
        -8956.343765693651,
        -7279.342111099715,
        -37913.41449671339,
        -6619.88209681458
      ],
      [
        -68820.74667791968,
        -8956.343765693651,
        30850.592136985477,
        11094.172830461343,
        30725.59609309348,
        5296.744124426119
      ],
      [
        -55871.19231256805,
        -7279.342111099715,
        11094.172830461343,
        8141.1711117702325,
        24772.237384237782,
        4278.705760417513
      ],
      [
        -283213.87856535264,
        -37913.41449671339,
        30725.59609309348,
        24772.237384237782,
        152306.55547332834,
        22525.850176665877
      ],
      [
        -49431.653988162696,
        -6619.88209681458,
        5296.744124426119,
        4278.705760417513,
        22525.850176665877,
        3838.6258685555167
      ]
    ],
    [
      [
        541350.2934492658,
        74903.11084648875,
        -69622.6262503139,
        -56925.84355731115,
        -203807.7178103305,
        -36078.83103405704
      ],
      [
        74903.11084648875,
        10387.948703502341,
        -9361.731993026417,
        -7663.632412706593,
        -28211.358824907198,
        -4996.928496335397
      ],
      [
        -69622.6262503139,
        -9361.731993026417,
        32533.473540461197,
        12492.999118006486,
        26649.464505582073,
        4653.788141028082
      ],
      [
        -56925.84355731115,
        -7663.632412706593,
        12492.999118006486,
        9310.44334641529,
        21635.65976602237,
        3785.940615721961
      ],
      [
        -203807.7178103305,
        -28211.358824907198,
        26649.464505582073,
        21635.65976602237,
        104552.26214307593,
        14387.920419120583
      ],
      [
        -36078.83103405704,
        -4996.928496335397,
        4653.788141028082,
        3785.940615721961,
        14387.920419120583,
        2452.301494792762
      ]
    ],
    [
      [
        466439.7824640776,
        66566.16983563305,
        -67987.78672673387,
        -56007.04352300432,
        -152259.35320181824,
        -27284.99980576909
      ],
      [
        66566.16983563305,
        9526.914228830052,
        -9412.987978029609,
        -7764.509725023519,
        -21738.889057936278,
        -3898.754006893132
      ],
      [
        -67987.78672673387,
        -9412.987978029609,
        33559.88159802411,
        13374.853331044971,
        22581.77500249799,
        3984.8621112758274
      ],
      [
        -56007.04352300432,
        -7764.509725023519,
        13374.853331044971,
        10073.321593243349,
        18464.597724051077,
        3265.5470851599366
      ],
      [
        -152259.35320181824,
        -21738.889057936278,
        22581.77500249799,
        18464.597724051077,
        77472.38659879215,
        9707.042673063226
      ],
      [
        -27284.99980576909,
        -3898.754006893132,
        3984.8621112758274,
        3265.5470851599366,
        9707.042673063226,
        1643.2860838089434
      ]
    ],
    [
      [
        415012.1836650761,
        60959.45244941739,
        -66144.06748320605,
        -54893.99730009737,
        -118635.85689039188,
        -21483.88349287565
      ],
      [
        60959.45244941739,
        8984.50558681588,
        -9408.15156632333,
        -7819.465869897759,
        -17434.10475324272,
        -3160.5533343929947
      ],
      [
        -66144.06748320605,
        -9408.15156632333,
        34258.70456421908,
        13997.782448961734,
        19252.728972141776,
        3426.4763961882845
      ],
      [
        -54893.99730009737,
        -7819.465869897759,
        13997.782448961734,
        10632.178209461365,
        15854.75359272414,
        2828.4849488663876
      ],
      [
        -118635.85689039188,
        -17434.10475324272,
        19252.728972141776,
        15854.75359272414,
        61645.03871550497,
        6938.496570632028
      ],
      [
        -21483.88349287565,
        -3160.5533343929947,
        3426.4763961882845,
        2828.4849488663876,
        6938.496570632028,
        1158.9429785718905
      ]
    ],
    [
      [
        379608.8691708944,
        57285.87974620778,
        -64647.486935579465,
        -54039.834808823056,
        -95849.77632941882,
        -17513.09797043843
      ],
      [
        57285.87974620778,
        8678.691607462746,
        -9430.739869276596,
        -7896.0932306217255,
        -14471.344636963906,
        -2647.7658470187666
      ],
      [
        -64647.486935579465,
        -9430.739869276596,
        34789.36572402969,
        14487.574746253003,
        16628.64247649751,
        2979.889854765036
      ],
      [
        -54039.834808823056,
        -7896.0932306217255,
        14487.574746253003,
        11086.210455769005,
        13789.925677620839,
        2477.5171511858766
      ],
      [
        -95849.77632941882,
        -14471.344636963906,
        16628.64247649751,
        13789.925677620839,
        51903.51942948314,
        5216.538241530197
      ],
      [
        -17513.09797043843,
        -2647.7658470187666,
        2979.889854765036,
        2477.5171511858766,
        5216.538241530197,
        854.4292589992446
      ]
    ],
    [
      [
        354915.81594283733,
        54938.27751511164,
        -63573.969620023076,
        -53512.63688713136,
        -79750.64732742691,
        -14681.06988652244
      ],
      [
        54938.27751511164,
        8541.388305795235,
        -9498.396814641312,
        -8009.306568524182,
        -12350.64640229239,
        -2277.4874517178223
      ],
      [
        -63573.969620023076,
        -9498.396814641312,
        35227.42616873149,
        14904.063599693134,
        14555.260173100945,
        2622.5181338021684
      ],
      [
        -53512.63688713136,
        -8009.306568524182,
        14904.063599693134,
        11482.763300090948,
        12153.603952822512,
        2195.731466861702
      ],
      [
        -79750.64732742691,
        -12350.64640229239,
        14555.260173100945,
        12153.603952822512,
        45598.605035742745,
        4091.4576226116214
      ],
      [
        -14681.06988652244,
        -2277.4874517178223,
        2622.5181338021684,
        2195.731466861702,
        4091.4576226116214,
        653.5066190506602
      ]
    ],
    [
      [
        337518.9645893034,
        53514.84919565587,
        -62877.243201826495,
        -53280.478507731044,
        -67939.40328221404,
        -12584.098721816023
      ],
      [
        53514.84919565587,
        8526.023258522464,
        -9609.988585001358,
        -8158.780866087367,
        -10777.060749384373,
        -2000.3121759102874
      ],
      [
        -62877.243201826495,
        -9609.988585001358,
        35610.37479221481,
        15277.008847974706,
        12894.542459819522,
        2332.8274968825554
      ],
      [
        -53280.478507731044,
        -8158.780866087367,
        15277.008847974706,
        11845.43621498878,
        10839.553306551968,
        1966.616937797015
      ],
      [
        -67939.40328221404,
        -10777.060749384373,
        12894.542459819522,
        10839.553306551968,
        41335.19753416668,
        3324.080338800185
      ],
      [
        -12584.098721816023,
        -2000.3121759102874,
        2332.8274968825554,
        1966.616937797015,
        3324.080338800185,
        515.2223576121919
      ]
    ],
    [
      [
        325236.8779170235,
        52754.21738530321,
        -62490.26251670529,
        -53293.09569706307,
        -58988.96568053412,
        -10980.29360280195
      ],
      [
        52754.21738530321,
        8601.74878445921,
        -9759.844352325668,
        -8340.375366677397,
        -9572.51298368664,
        -1786.19778639794
      ],
      [
        -62490.26251670529,
        -9759.844352325668,
        35957.95474208069,
        15622.107902872547,
        11542.77596193042,
        2094.2553843533196
      ],
      [
        -53293.09569706307,
        -8340.375366677397,
        15622.107902872547,
        12186.69068655803,
        9767.387166107623,
        1777.371869534954
      ],
      [
        -58988.96568053412,
        -9572.51298368664,
        11542.77596193042,
        9767.387166107623,
        38343.305810385966,
        2781.289407642533
      ],
      [
        -10980.29360280195,
        -1786.19778639794,
        2094.2553843533196,
        1777.371869534954,
        2781.289407642533,
        416.5909297690525
      ]
    ],
    [
      [
        316647.0133677557,
        52483.77745842206,
        -62352.04770879037,
        -53503.93632558394,
        -52017.69516233113,
        -9719.338736587186
      ],
      [
        52483.77745842206,
        8747.969727777136,
        -9941.967672906892,
        -8549.5601258826,
        -8625.682161556178,
        -1616.2597485930983
      ],
      [
        -62352.04770879037,
        -9941.967672906892,
        36281.20075978468,
        15948.139753550106,
        10425.087502114973,
        1894.688485689019
      ],
      [
        -53503.93632558394,
        -8549.5601258826,
        15948.139753550106,
        12513.495299627739,
        8878.843053855451,
        1618.5943983701404
      ],
      [
        -52017.69516233113,
        -8625.682161556178,
        10425.087502114973,
        8878.843053855451,
        36176.977728501806,
        2385.409364199552
      ],
      [
        -9719.338736587186,
        -1616.2597485930983,
        1894.688485689019,
        1618.5943983701404,
        2385.409364199552,
        344.09879149571464
      ]
    ],
    [
      [
        310796.3030417224,
        52586.7780915089,
        -62412.939913128146,
        -53874.769324838984,
        -46460.071540871715,
        -8704.335314158277
      ],
      [
        52586.7780915089,
        8950.663425648754,
        -10151.153716654144,
        -8782.353483978666,
        -7864.451681888717,
        -1478.2088284414776
      ],
      [
        -62412.939913128146,
        -10151.153716654144,
        36586.63479078509,
        16260.290944958011,
        9487.558809141909,
        1725.3272229325332
      ],
      [
        -53874.769324838984,
        -8782.353483978666,
        16260.290944958011,
        12829.961101438457,
        8131.854225264832,
        1483.4368561513306
      ],
      [
        -46460.071540871715,
        -7864.451681888717,
        9487.558809141909,
        8131.854225264832,
        34566.265280485735,
        2089.0966426948034
      ],
      [
        -8704.335314158277,
        -1478.2088284414776,
        1725.3272229325332,
        1483.4368561513306,
        2089.0966426948034,
        289.45210286917296
      ]
    ],
    [
      [
        307028.45183504355,
        52982.20709263934,
        -62633.90756392909,
        -54375.38808282192,
        -41940.613290312,
        -7870.665880291754
      ],
      [
        52982.20709263934,
        9200.06783100307,
        -10383.155081329178,
        -9035.483703518265,
        -7240.526556248315,
        -1363.7837649537564
      ],
      [
        -62633.90756392909,
        -10383.155081329178,
        36878.31679431356,
        16561.785182916654,
        8690.957833483764,
        1579.726620771483
      ],
      [
        -54375.38808282192,
        -9035.483703518265,
        16561.785182916654,
        13138.63579388375,
        7495.752468626695,
        1366.8748561986458
      ],
      [
        -41940.613290312,
        -7240.526556248315,
        8690.957833483764,
        7495.752468626695,
        33341.23986627953,
        1862.356984899754
      ],
      [
        -7870.665880291754,
        -1363.7837649537564,
        1579.726620771483,
        1366.8748561986458,
        1862.356984899754,
        247.36203683171468
      ]
    ],
    [
      [
        304879.73333566944,
        53612.46201129948,
        -62984.56115484038,
        -54982.184799322975,
        -38202.20878210489,
        -7173.910436457523
      ],
      [
        53612.46201129948,
        9489.239063379371,
        -10634.576680684364,
        -9306.323535706139,
        -6720.584362845373,
        -1267.2657220100386
      ],
      [
        -62984.56115484038,
        -10634.576680684364,
        37158.89885455241,
        16854.722660420382,
        8006.313993305606,
        1453.1019086883784
      ],
      [
        -54982.184799322975,
        -9306.323535706139,
        16854.722660420382,
        13441.17160464504,
        6947.856016681727,
        1265.1733225928767
      ],
      [
        -38202.20878210489,
        -6720.584362845373,
        8006.313993305606,
        6947.856016681727,
        32391.202193280646,
        1685.5317845766072
      ],
      [
        -7173.910436457523,
        -1267.2657220100386,
        1453.1019086883784,
        1265.1733225928767,
        1685.5317845766072,
        214.34072723299806
      ]
    ],
    [
      [
        304014.7050215712,
        54435.655164627125,
        -63441.210144894954,
        -55676.699185182995,
        -35063.92540959938,
        -6582.698686115213
      ],
      [
        54435.655164627125,
        9813.139696965458,
        -10902.716648862259,
        -9592.774969366,
        -6281.014696977108,
        -1184.5909928539381
      ],
      [
        -63441.210144894954,
        -10902.716648862259,
        37430.19269295559,
        17140.53271915808,
        7411.892235765741,
        1341.8467708373446
      ],
      [
        -55676.699185182995,
        -9592.774969366,
        17140.53271915808,
        13738.686068084337,
        6471.125877547605,
        1175.514211453435
      ],
      [
        -35063.92540959938,
        -6281.014696977108,
        7411.892235765741,
        6471.125877547605,
        31641.840304412948,
        1545.3479191465499
      ],
      [
        -6582.698686115213,
        -1184.5909928539381,
        1341.8467708373446,
        1175.514211453435,
        1545.3479191465499,
        188.01924812850376
      ]
    ],
    [
      [
        304185.53691697883,
        55420.700748014075,
        -63985.2756654675,
        -56444.41523841721,
        -32395.3259222259,
        -6074.340960161651
      ],
      [
        55420.700748014075,
        10168.051020610783,
        -11185.41860350799,
        -9893.158894168402,
        -5904.6900176112995,
        -1112.8041815049933
      ],
      [
        -63985.2756654675,
        -11185.41860350799,
        37693.48831889908,
        17420.228373531725,
        6891.129931605257,
        1243.2017524321332
      ],
      [
        -56444.41523841721,
        -9893.158894168402,
        17420.228373531725,
        14031.965150961561,
        6052.563243799975,
        1095.7394612790063
      ],
      [
        -32395.3259222259,
        -5904.6900176112995,
        6891.129931605257,
        6052.563243799975,
        31041.936933937475,
        1432.6067395354307
      ],
      [
        -6074.340960161651,
        -1112.8041815049933,
        1243.2017524321332,
        1095.7394612790063,
        1432.6067395354307,
        166.7464882758322
      ]
    ],
    [
      [
        305205.6234971013,
        56544.10349754589,
        -64602.07044340648,
        -57273.82903210136,
        -30100.34208394538,
        -5632.075004209754
      ],
      [
        56544.10349754589,
        10551.18587398257,
        -11480.950689912454,
        -10206.12355155283,
        -5578.9232651038055,
        -1049.7111672641854
      ],
      [
        -64602.07044340648,
        -11480.950689912454,
        37949.73987778564,
        17694.55491624539,
        6431.218635702771,
        1155.0247356407647
      ],
      [
        -57273.82903210136,
        -10206.12355155283,
        17694.55491624539,
        14321.581960444906,
        5682.105489876072,
        1024.1726750539433
      ],
      [
        -30100.34208394538,
        -5578.9232651038055,
        6431.218635702771,
        5682.105489876072,
        30555.362153984104,
        1340.7849637619313
      ],
      [
        -5632.075004209754,
        -1049.7111672641854,
        1155.0247356407647,
        1024.1726750539433,
        1340.7849637619313,
        149.34509454069365
      ]
    ],
    [
      [
        306932.0480037829,
        57787.811234372,
        -65279.8815680942,
        -58155.7443645037,
        -28106.859854254333,
        -5243.282084773083
      ],
      [
        57787.811234372,
        10960.428084860083,
        -11787.91109584897,
        -10530.572473197415,
        -5294.140211867055,
        -993.6528354958384
      ],
      [
        -65279.8815680942,
        -11787.91109584897,
        38199.6778532862,
        17964.0796961391,
        6022.116607092606,
        1075.6302719619002
      ],
      [
        -58155.7443645037,
        -10530.572473197415,
        17964.0796961391,
        14607.968497651036,
        5351.856227798079,
        959.4940925222036
      ],
      [
        -28106.859854254333,
        -5294.140211867055,
        6022.116607092606,
        5351.856227798079,
        30156.098425832603,
        1265.1612753782156
      ],
      [
        -5243.282084773083,
        -993.6528354958384,
        1075.6302719619002,
        959.4940925222036,
        1265.1612753782156,
        134.95839435926266
      ]
    ],
    [
      [
        309253.667270968,
        59137.74779118359,
        -66009.28507917773,
        -59082.74456457338,
        -26359.819407931944,
        -4898.301616969182
      ],
      [
        59137.74779118359,
        11394.1534944964,
        -12105.155571608382,
        -10865.608923911077,
        -5042.9946644616675,
        -943.3538773701305
      ],
      [
        -66009.28507917773,
        -12105.155571608382,
        38443.878986834214,
        18229.24807642506,
        5655.851251692922,
        1003.675591523178
      ],
      [
        -59082.74456457338,
        -10865.608923911077,
        18229.24807642506,
        14891.460384149737,
        5055.540697577626,
        900.6517724246446
      ],
      [
        -26359.819407931944,
        -5042.9946644616675,
        5655.851251692922,
        5055.540697577626,
        29825.062974930028,
        1202.25591656667
      ],
      [
        -4898.301616969182,
        -943.3538773701305,
        1003.675591523178,
        900.6517724246446,
        1202.25591656667,
        122.95172784368324
      ]
    ],
    [
      [
        312082.8479391201,
        60582.790665537,
        -66782.632944302,
        -60048.79608848598,
        -24816.53706968798,
        -4589.625297682845
      ],
      [
        60582.790665537,
        11851.104653062283,
        -12431.742115819925,
        -11210.493348023656,
        -4819.765331080784,
        -897.8194720509889
      ],
      [
        -66782.632944302,
        -12431.742115819925,
        38682.811137948236,
        18490.419327593016,
        5326.019041247013,
        938.0785815721877
      ],
      [
        -60048.79608848598,
        -11210.493348023656,
        18490.419327593016,
        15172.32553692641,
        4788.1149019878485,
        846.7976188227094
      ],
      [
        -24816.53706968798,
        -4819.765331080784,
        5326.019041247013,
        4788.1149019878485,
        29548.027151748494,
        1149.462136467191
      ],
      [
        -4589.625297682845,
        -897.8194720509889,
        938.0785815721877,
        846.7976188227094,
        1149.462136467191,
        112.84727335903823
      ]
    ],
    [
      [
        315349.62643118436,
        62114.0454495985,
        -67593.66698904123,
        -61048.94957488359,
        -23443.466711853984,
        -4311.337782815088
      ],
      [
        62114.0454495985,
        12330.301525777266,
        -12766.888710527059,
        -11564.610763362558,
        -4619.936181745863,
        -856.2632423824291
      ],
      [
        -67593.66698904123,
        -12766.888710527059,
        38916.862860263565,
        18747.890271869517,
        5027.42179864186,
        877.9579396601087
      ],
      [
        -61048.94957488359,
        -11564.610763362558,
        18747.890271869517,
        15450.783037754916,
        4545.4810543527565,
        797.2406636759048
      ],
      [
        -23443.466711853984,
        -4619.936181745863,
        5027.42179864186,
        4545.4810543527565,
        29314.22329131721,
        1104.7983735970643
      ],
      [
        -4311.337782815088,
        -856.2632423824291,
        877.9579396601087,
        797.2406636759048,
        1104.7983735970643,
        104.2800367439327
      ]
    ],
    [
      [
        318997.51027452206,
        63724.32217918254,
        -68437.22625598246,
        -62079.1128460813,
        -22213.914789793787,
        -4058.7211175871817
      ],
      [
        63724.32217918254,
        12830.97681669027,
        -13109.940883251957,
        -11927.445679832192,
        -4439.898993644956,
        -818.0560837600025
      ],
      [
        -68437.22625598246,
        -13109.940883251957,
        39146.36340814553,
        19001.911255370556,
        4755.798497075392,
        822.5889163170998
      ],
      [
        -62079.1128460813,
        -11927.445679832192,
        19001.911255370556,
        15727.015858068631,
        4324.277575148231,
        751.4124945558833
      ],
      [
        -22213.914789793787,
        -4439.898993644956,
        4755.798497075392,
        4324.277575148231,
        29115.392880541367,
        1066.7382456006317
      ],
      [
        -4058.7211175871817,
        -818.0560837600025,
        822.5889163170998,
        751.4124945558833,
        1066.7382456006317,
        96.96753339587757
      ]
    ],
    [
      [
        322980.4114652837,
        65407.75152315344,
        -69309.02335540805,
        -63135.87716139298,
        -21106.400165001418,
        -3827.97015025209
      ],
      [
        65407.75152315344,
        13352.52841140685,
        -13460.346652019514,
        -12298.562689313398,
        -4276.7389009659355,
        -782.6892031470408
      ],
      [
        -69309.02335540805,
        -13460.346652019514,
        39371.59659762456,
        19252.69719177903,
        4507.624901450919,
        771.370166134662
      ],
      [
        -63135.87716139298,
        -12298.562689313398,
        19252.69719177903,
        16001.179636137247,
        4121.7220909494,
        708.8413443269358
      ],
      [
        -21106.400165001418,
        -4276.7389009659355,
        4507.624901450919,
        4121.7220909494,
        28945.124222171493,
        1034.091776430986
      ],
      [
        -3827.97015025209,
        -782.6892031470408,
        771.370166134662,
        708.8413443269358,
        1034.091776430986,
        90.68852190768614
      ]
    ],
    [
      [
        327260.3740937243,
        67159.4994603468,
        -70205.47210261645,
        -64216.383134024196,
        -20103.45810302545,
        -3615.984570230541
      ],
      [
        67159.4994603468,
        13894.483921732404,
        -13817.637036611293,
        -12677.591342537702,
        -4128.077376843701,
        -749.7470097025925
      ],
      [
        -70205.47210261645,
        -13817.637036611293,
        39592.81063322283,
        19500.435371688687,
        4279.962055574151,
        723.7986193383422
      ],
      [
        -64216.383134024196,
        -12677.591342537702,
        19500.435371688687,
        16273.408864419294,
        3935.492627030855,
        669.1324397410029
      ],
      [
        -20103.45810302545,
        -4128.077376843701,
        4279.962055574151,
        3935.492627030855,
        28798.38379990182,
        1005.9210340699376
      ],
      [
        -3615.984570230541,
        -749.7470097025925,
        723.7986193383422,
        669.1324397410029,
        1005.9210340699376,
        85.2678393159929
      ]
    ],
    [
      [
        331805.8680111679,
        68975.55238643002,
        -71123.55355838197,
        -65318.2163963593,
        -19190.755516407815,
        -3420.2147524218817
      ],
      [
        68975.55238643002,
        14456.473913424583,
        -14181.410786158842,
        -13064.2142802546,
        -3991.9556262068672,
        -718.8869499481235
      ],
      [
        -71123.55355838197,
        -14181.410786158842,
        39810.22522838998,
        19745.29110355436,
        4070.34039349021,
        679.4502176248737
      ],
      [
        -65318.2163963593,
        -13064.2142802546,
        19745.29110355436,
        16543.821342013962,
        3763.6366763165906,
        631.9529292972213
      ],
      [
        -19190.755516407815,
        -3991.9556262068672,
        4070.34039349021,
        3763.6366763165906,
        28671.179608371098,
        981.4792964369178
      ],
      [
        -3420.2147524218817,
        -718.8869499481235,
        679.4502176248737,
        631.9529292972213,
        981.4792964369178,
        80.56542351185999
      ]
    ],
    [
      [
        336590.4917339955,
        70852.55329771561,
        -72060.71104714621,
        -66439.32574165658,
        -18356.427749389793,
        -3238.545977018618
      ],
      [
        70852.55329771561,
        15038.211449349777,
        -14551.322318751954,
        -13458.157847547905,
        -3866.7468548791976,
        -689.824313704281
      ],
      [
        -72060.71104714621,
        -14551.322318751954,
        40024.0368709286,
        19987.411869671465,
        3876.670150238654,
        637.9649892552873
      ],
      [
        -66439.32574165658,
        -13458.157847547905,
        19987.411869671465,
        16812.52144013015,
        3604.500861838731,
        597.0202014147944
      ],
      [
        -18356.427749389793,
        -3866.7468548791976,
        3876.670150238654,
        3604.500861838731,
        28560.31588698339,
        960.1665713065431
      ],
      [
        -3238.545977018618,
        -689.824313704281,
        637.9649892552873,
        597.0202014147944,
        960.1665713065431,
        76.46825642861613
      ]
    ],
    [
      [
        341591.9752742635,
        72787.67552116205,
        -73014.76723548734,
        -67577.95839904704,
        -17590.57535160074,
        -3069.210415477068
      ],
      [
        72787.67552116205,
        15639.476288328238,
        -14927.072127984215,
        -13859.18461854621,
        -3751.089469207114,
        -662.3206487482714
      ],
      [
        -73014.76723548734,
        -14927.072127984215,
        40234.42279537415,
        20226.930448836683,
        3697.1714131945414,
        599.0353716658632
      ],
      [
        -67577.95839904704,
        -13859.18461854621,
        20226.930448836683,
        17079.60254323561,
        3456.6759882300657,
        564.0927412009192
      ],
      [
        -17590.57535160074,
        -3751.089469207114,
        3697.1714131945414,
        3456.6759882300657,
        28463.212132880963,
        941.4966566493388
      ],
      [
        -3069.210415477068,
        -662.3206487482714,
        599.0353716658632,
        564.0927412009192,
        941.4966566493388,
        72.88437549741836
      ]
    ],
    [
      [
        346791.4054938954,
        74778.5243767383,
        -73983.85813402548,
        -68732.60846603265,
        -16884.877936852325,
        -2910.7194736503084
      ],
      [
        74778.5243767383,
        16260.10255626179,
        -15308.399096339333,
        -14267.087399688055,
        -3643.835647010612,
        -636.1748296557848
      ],
      [
        -73983.85813402548,
        -15308.399096339333,
        40441.544035615625,
        20463.967305382525,
        3530.318999639053,
        562.39699046874
      ],
      [
        -68732.60846603265,
        -14267.087399688055,
        20463.967305382525,
        17345.148906162845,
        3318.953716685375,
        532.9629082149532
      ],
      [
        -16884.877936852325,
        -3643.835647010612,
        3530.318999639053,
        3318.953716685375,
        28377.767955062583,
        925.0724587472771
      ],
      [
        -2910.7194736503084,
        -636.1748296557848,
        562.39699046874,
        532.9629082149532,
        925.0724587472771,
        69.73837011233087
      ]
    ],
    [
      [
        352172.6184274005,
        76823.05984823382,
        -74966.3801782552,
        -69901.9755187023,
        -16232.294789761305,
        -2761.8112437557893
      ],
      [
        76823.05984823382,
        16899.969033991147,
        -15695.074291476467,
        -14681.68438403345,
        -3544.011334919116,
        -611.2161024127784
      ],
      [
        -74966.3801782552,
        -15695.074291476467,
        40645.547810411554,
        20698.632447222226,
        3374.7986398957014,
        527.821315099414
      ],
      [
        -69901.9755187023,
        -14681.68438403345,
        20698.632447222226,
        17609.237089504204,
        3190.2921079851717,
        503.45118240862433
      ],
      [
        -16232.294789761305,
        -3544.011334919116,
        3374.7986398957014,
        3190.2921079851717,
        28302.261046266678,
        910.567295674374
      ],
      [
        -2761.8112437557893,
        -611.2161024127784,
        527.821315099414,
        503.45118240862433,
        910.567295674374,
        66.96795806219522
      ]
    ],
    [
      [
        357721.71833093464,
        78919.53524301513,
        -75960.94751555976,
        -71084.93117313337,
        -15626.830487621815,
        -2621.409298988391
      ],
      [
        78919.53524301513,
        17558.99144209135,
        -16086.895928381742,
        -15102.815211918238,
        -3450.7848370643705,
        -587.2986165429003
      ],
      [
        -75960.94751555976,
        -16086.895928381742,
        40846.56942087506,
        20931.02689686302,
        3229.471864802196,
        495.1097619562075
      ],
      [
        -71084.93117313337,
        -15102.815211918238,
        20931.02689686302,
        17871.937088912684,
        3069.787996725153,
        475.4015429058139
      ],
      [
        -15626.830487621815,
        -3450.7848370643705,
        3229.471864802196,
        3069.787996725153,
        28235.269369670415,
        897.7105911395333
      ],
      [
        -2621.409298988391,
        -587.2986165429003,
        495.1097619562075,
        475.4015429058139,
        897.7105911395333,
        64.5213567435188
      ]
    ],
    [
      [
        363426.69378252083,
        81066.44812064755,
        -76966.3572935425,
        -72280.49188452947,
        -15063.349765132838,
        -2488.5900929879763
      ],
      [
        81066.44812064755,
        18237.116260168405,
        -16483.685249804188,
        -15530.337745996196,
        -3363.4419305549663,
        -564.2970886979344
      ],
      [
        -76966.3572935425,
        -16483.685249804188,
        41044.73378030946,
        21161.243871597675,
        3093.347653684666,
        464.0889237525788
      ],
      [
        -72280.49188452947,
        -15530.337745996196,
        21161.243871597675,
        18133.31323506692,
        2956.6546737146055,
        448.67772844841966
      ],
      [
        -15063.349765132838,
        -3363.4419305549663,
        3093.347653684666,
        2956.6546737146055,
        28175.61124901705,
        886.2768245529255
      ],
      [
        -2488.5900929879763,
        -564.2970886979344,
        464.0889237525788,
        448.67772844841966,
        886.2768245529255,
        62.355245750331434
      ]
    ]
  ]
}